pycounts_ljq_mds/__init__.py
pycounts_ljq_mds/plotting.py
pycounts_ljq_mds/pycounts_ljq_mds.py
pycounts_ljq_mds-0.1.0.dist-info/LICENSE
pycounts_ljq_mds-0.1.0.dist-info/METADATA
pycounts_ljq_mds-0.1.0.dist-info/WHEEL
pycounts_ljq_mds-0.1.0.dist-info/RECORD
